nonebot_plugin_poker_reloaded/__init__.py
nonebot_plugin_poker_reloaded/utils.py
nonebot_plugin_poker_reloaded-0.1.0.dist-info/LICENSE
nonebot_plugin_poker_reloaded-0.1.0.dist-info/METADATA
nonebot_plugin_poker_reloaded-0.1.0.dist-info/WHEEL
nonebot_plugin_poker_reloaded-0.1.0.dist-info/RECORD
