Metadata-Version: 2.3
Name: nonebot_plugin_poker_reloaded
Version: 0.1.0
Summary: Nonebot2 plugin for poker-reloaded
License: MIT
Author: haorwen
Author-email: haorwen@qq.com
Requires-Python: >=3.9,<4.0
Classifier: License :: OSI Approved :: MIT License
Classifier: Programming Language :: Python :: 3
Classifier: Programming Language :: Python :: 3.9
Classifier: Programming Language :: Python :: 3.10
Classifier: Programming Language :: Python :: 3.11
Classifier: Programming Language :: Python :: 3.12
Classifier: Programming Language :: Python :: 3.13
Requires-Dist: nonebot-plugin-alconna (>=0.38.0,<1.0.0)
Requires-Dist: nonebot2 (>=2.3.0,<3.0.0)
Project-URL: Homepage, https://github.com/haorwen/nonebot-plugin-poker-reloaded
Project-URL: Repository, https://github.com/haorwen/nonebot-plugin-poker-reloaded
